<?xml version="1.0" encoding="UTF-8"?>
<openerp>
    <data>
        <!-- Suppression des comptes 4011, 4017-->
        <record model="account.account.template" id="l10n_fr.fr_pcg_pay">
            <field name="active" eval="False" />
        </record>
        <record model="account.account.template" id="l10n_fr.pcg_4017">
            <field name="active" eval="False" />
        </record>
        <!-- Changement du type de compte 401 (compte 'vue' a compte 'client') -->
        <record model="account.account.template" id="l10n_fr.pcg_401">
            <field name="type">payable</field>
        </record>

        <!-- Suppression des comptes 4111, 4117-->
        <record model="account.account.template" id="l10n_fr.fr_pcg_recv">
            <field name="active" eval="False" />
        </record>
        <record model="account.account.template" id="l10n_fr.pcg_4117">
            <field name="active" eval="False" />
        </record>
        <!-- Changement du type de compte 411 (compte 'vue' a compte 'fournisseur') -->
        <record model="account.account.template" id="l10n_fr.pcg_411">
            <field name="type">receivable</field>
        </record>

        <!-- Création d'un nouveau compte 5312-->
        <record model="account.account.template" id="pcg_5312">
            <field name="name">Caisse pour Petits achats</field>
            <field name="code">5312</field>
            <field name="type">other</field>
            <field name="user_type" ref="account.data_account_type_cash"/>
            <field name="parent_id" ref="l10n_fr.pcg_531"/>
        </record>

        <!-- Suppression des comptes 6011, 6012, 6013-->
        <record model="account.account.template" id="l10n_fr.pcg_6011">
            <field name="active" eval="False" />
        </record>
        <record model="account.account.template" id="l10n_fr.pcg_6012">
            <field name="active" eval="False" />
        </record>
        <record model="account.account.template" id="l10n_fr.pcg_6017">
            <field name="active" eval="False" />
        </record>
        <!-- Changement du type de compte 601 (compte 'vue' a compte 'normal') -->
        <record model="account.account.template" id="l10n_fr.pcg_601">
            <field name="type">other</field>
        </record>

        <!-- Renommage du compte 6071-->
        <record model="account.account.template" id="l10n_fr.pcg_6071">
            <field name="name">Achats de marchandises externes</field>
        </record>

        <!-- Renommage des comptes 609x-->
        <record model="account.account.template" id="l10n_fr.pcg_6091">
            <field name="name">RRR sur achats de matières premières (et fournitures)</field>
        </record>
        <record model="account.account.template" id="l10n_fr.pcg_6092">
            <field name="name">RRR sur achats d'autres approvisionnements stockés</field>
        </record>
        <record model="account.account.template" id="l10n_fr.pcg_6094">
            <field name="name">RRR sur achats d'études et prestations de services</field>
        </record>
        <record model="account.account.template" id="l10n_fr.pcg_6095">
            <field name="name">RRR sur achats de matériel, équipements et travaux</field>
        </record>
        <record model="account.account.template" id="l10n_fr.pcg_6096">
            <field name="name">RRR sur achats d'approvisionnements non stockés</field>
        </record>
        <record model="account.account.template" id="l10n_fr.pcg_6097">
            <field name="name">RRR sur achats de marchandises</field>
        </record>

        <!-- Renommage du compte 6338-->
        <record model="account.account.template" id="l10n_fr.pcg_6338" >
            <field name="name">Autres Taxes</field>
        </record>

        <!-- Changement du type de compte 658 (compte 'normal' a compte 'vue') -->
        <record model="account.account.template" id="l10n_fr.pcg_658">
          <field name="type">view</field>
        </record>
        <!-- Creation d'un sous-compte 6581 -->
        <record model="account.account.template" id="pcg_6581">
            <field name="name">Fond de caisse (D)</field>
            <field name="code">6581</field>
            <field name="type">other</field>
            <field name="user_type" ref="account.data_account_type_expense"/>
            <field name="parent_id" ref="l10n_fr.pcg_658"/>
        </record>
        <!-- Creation d'un sous-compte 6582 -->
        <record model="account.account.template" id="pcg_7582">
            <field name="name">Erreurs de caisse</field>
            <field name="code">6582</field>
            <field name="type">other</field>
            <field name="user_type" ref="account.data_account_type_expense"/>
            <field name="parent_id" ref="l10n_fr.pcg_658"/>
        </record>

        <!-- Suppression des comptes 7011, 7012 -->
        <record model="account.account.template" id="l10n_fr.pcg_7011">
            <field name="active" eval="False" />
        </record>
        <record model="account.account.template" id="l10n_fr.pcg_7012">
            <field name="active" eval="False" />
        </record>
        <!-- Changement du type de compte 701 (compte 'vue' a compte 'normal') -->
        <record model="account.account.template" id="l10n_fr.pcg_701">
            <field name="type">other</field>
        </record>

        <!-- Suppression des comptes 7071, 7072, 7073-->
        <record model="account.account.template" id="l10n_fr.pcg_7071">
            <field name="active" eval="False" />
        </record>
        <record model="account.account.template" id="l10n_fr.pcg_7072">
            <field name="active" eval="False" />
        </record>
        <record model="account.account.template" id="l10n_fr.pcg_7073">
            <field name="active" eval="False" />
        </record>
        <!-- Changement du type de compte 707 (compte 'vue' a compte 'normal') -->
        <record model="account.account.template" id="l10n_fr.fr_pcg_sale">
            <field name="type">other</field>
        </record>

        <!-- Renommage des comptes 709x-->
        <record model="account.account.template" id="l10n_fr.pcg_7091">
            <field name="name">RRR sur ventes de produits finis</field>
        </record>
        <record model="account.account.template" id="l10n_fr.pcg_7092">
            <field name="name">RRR sur ventes de produits intermédiaires</field>
        </record>
        <record model="account.account.template" id="l10n_fr.pcg_7094">
            <field name="name">RRR sur travaux</field>
        </record>
        <record model="account.account.template" id="l10n_fr.pcg_7095">
            <field name="name">RRR sur études</field>
        </record>
        <record model="account.account.template" id="l10n_fr.pcg_7096">
            <field name="name">RRR sur prestations de services</field>
        </record>
        <record model="account.account.template" id="l10n_fr.pcg_7097">
            <field name="name">RRR sur ventes de marchandises</field>
        </record>

        <!-- Changement du type de compte 758 (compte 'normal' a compte 'vue') -->
        <record model="account.account.template" id="l10n_fr.pcg_758">
            <field name="type">view</field>
        </record>
        <!-- Creation d'un sous-compte 7581 -->
        <record model="account.account.template" id="pcg_7581">
            <field name="name">Fond de caisse (C)</field>
            <field name="code">7581</field>
            <field name="type">other</field>
            <field name="user_type" ref="account.data_account_type_income"/>
            <field name="parent_id" ref="l10n_fr.pcg_758"/>
        </record>
        <!-- Creation d'un sous-compte 7582 -->
        <record model="account.account.template" id="pcg_7582">
            <field name="name">Erreurs de caisse</field>
            <field name="code">7582</field>
            <field name="type">other</field>
            <field name="user_type" ref="account.data_account_type_income"/>
            <field name="parent_id" ref="l10n_fr.pcg_758"/>
        </record>

    </data>
</openerp>
